comic_ocr/__init__.py
comic_ocr/dataset/__init__.py
comic_ocr/dataset/annotated_manga/__init__.py
comic_ocr/dataset/generated_manga/__init__.py
comic_ocr/dataset/generated_manga/generator.py
comic_ocr/dataset/generated_manga/text_area.py
comic_ocr/dataset/generated_manga/text_bubble.py
comic_ocr/dataset/generated_manga/text_rect.py
comic_ocr/dataset/generated_single_line/__init__.py
comic_ocr/dataset/generated_single_line/generator.py
comic_ocr/hub.py
comic_ocr/models/__init__.py
comic_ocr/models/localization/__init__.py
comic_ocr/models/localization/conv_unet/__init__.py
comic_ocr/models/localization/conv_unet/conv_fpn.py
comic_ocr/models/localization/conv_unet/conv_unet.py
comic_ocr/models/localization/localization_dataset.py
comic_ocr/models/localization/localization_model.py
comic_ocr/models/localization/localization_open_cv.py
comic_ocr/models/localization/localization_utils.py
comic_ocr/models/localization/train.py
comic_ocr/models/recognition/__init__.py
comic_ocr/models/recognition/crnn/__init__.py
comic_ocr/models/recognition/crnn/crnn.py
comic_ocr/models/recognition/crnn/transformer_crnn.py
comic_ocr/models/recognition/encoding.py
comic_ocr/models/recognition/fcn/__init__.py
comic_ocr/models/recognition/fcn/fcn.py
comic_ocr/models/recognition/recognition_dataset.py
comic_ocr/models/recognition/recognition_model.py
comic_ocr/models/recognition/recognition_utils.py
comic_ocr/models/recognition/train.py
comic_ocr/models/recognition/trocr/__init__.py
comic_ocr/models/recognition/trocr/trocr.py
comic_ocr/models/train_helpers.py
comic_ocr/models/transforms.py
comic_ocr/types/__init__.py
comic_ocr/types/files.py
comic_ocr/types/images.py
comic_ocr/types/lines.py
comic_ocr/types/shapes.py
comic_ocr/utils/__init__.py
comic_ocr/utils/examples.py
comic_ocr/utils/files.py
comic_ocr/utils/nb_annotation.py
comic_ocr/utils/plotting.py
comic_ocr/utils/pytorch_model.py
example/manga_annotated/xkcd_100.jpg
comic_ocr-0.1.6.dist-info/WHEEL
comic_ocr-0.1.6.dist-info/METADATA
comic_ocr-0.1.6.dist-info/RECORD
