Metadata-Version: 2.1
Name: comic-ocr
Version: 0.1.6
Summary: An OCR library comic and manga
License: MIT
Author: Wanasit T
Requires-Python: >=3.8,<4.0
Classifier: License :: OSI Approved :: MIT License
Classifier: Programming Language :: Python :: 3
Classifier: Programming Language :: Python :: 3.10
Classifier: Programming Language :: Python :: 3.8
Classifier: Programming Language :: Python :: 3.9
Requires-Dist: Pillow (>=9.1,<10.0)
Requires-Dist: numpy (>=1.21,<2.0)
Requires-Dist: opencv-python (>=4.5.4.60,<5.0.0.0)
Requires-Dist: textdistance (>=4.2.1,<5.0.0)
Requires-Dist: torch (>=1.12.1,<2.0.0)
Requires-Dist: torchvision (>=0.13.1,<0.14.0)
Requires-Dist: tqdm (>=4,<5)
Requires-Dist: transformers (>=4.23.1,<5.0.0)
